majormode/__init__.py
majormode/heritagego/__init__.py
majormode/heritagego/model/__init__.py
majormode/heritagego/model/contest.py
majormode/heritagego/model/heritagego.py
heritagego_core_library-1.0.0.dist-info/METADATA
heritagego_core_library-1.0.0.dist-info/WHEEL
heritagego_core_library-1.0.0.dist-info/top_level.txt
heritagego_core_library-1.0.0.dist-info/RECORD
