Metadata-Version: 2.1
Name: heritagego-core-library
Version: 1.0.0
Summary: Héritage GO Core Python Library
Home-page: http://www.heritagego.org/
Author: Daniel CAUNE
Author-email: daniel.caune@heritageobservatory.org
License: Copyright (C) 2019 Heritage Observatory. All rights reserved.
Platform: any
Classifier: License :: OSI Approved :: GNU General Public License (GPL)
Classifier: Development Status :: 5 - Production/Stable
Classifier: Topic :: Software Development :: Libraries :: Python Modules
Classifier: Programming Language :: Python
Requires-Python: >=3
Requires-Dist: perseus-core-library
Requires-Dist: pipfile
Requires-Dist: setuptools
Requires-Dist: wheel
Requires-Dist: twine
